aioreqs/__init__.py
aioreqs/aiofy.py
aioreqs/sync/__init__.py
aioreqs-1.3.0.dist-info/WHEEL
aioreqs-1.3.0.dist-info/entry_points.txt
aioreqs-1.3.0.dist-info/METADATA
aioreqs-1.3.0.dist-info/RECORD
