Metadata-Version: 2.3
Name: aioreqs
Version: 1.3.0
Summary: Simple async wrapper for `requests` library
Author: Xenely
Author-email: Xenely <amaryatkin@vk.com>
Requires-Dist: requests>=2.32.5
Requires-Python: >=3.10
